<?xml version="1.0" encoding="utf-8" ?><dwsync><file name="styles.css" server="sftp.sd5.gpaas.net/vhosts/www.thesomethinrain.work/" local="3598417818" remote="320909690688832820" Dst="-1" /><file name="styles.css.map" server="sftp.sd5.gpaas.net/vhosts/www.thesomethinrain.work/" local="3598417819" remote="320909690688832820" Dst="-1" /><file name="styles.css" server="sftp.sd5.gpaas.net/vhosts/www.thesomethinrain.work/htdocs/" local="3598612913" remote="321296718781905347" Dst="-1" /><file name="styles.css" server="sftp.sd5.gpaas.net/vhosts/d2509634376c4fa096dd69c4f55a4de8.testmyurl.ws/" local="3598612913" remote="320944875078813490" Dst="-1" /><file name="styles.css.map" server="sftp.sd5.gpaas.net/vhosts/d2509634376c4fa096dd69c4f55a4de8.testmyurl.ws/" local="3598612914" remote="320944875078813491" Dst="-1" /><file name="styles.css" server="sftp.sd5.gpaas.net/vhosts/thesomethinrain.work/htdocs/" local="3616474297" remote="3665077186" Dst="-1" /><file name="styles.css.map" server="sftp.sd5.gpaas.net/vhosts/thesomethinrain.work/htdocs/" local="3598612914" remote="3665077187" Dst="-1" /><file name="styles.css" server="sftp.sd3.gpaas.net/vhosts/default/" local="3616474297" remote="3777036033" Dst="-1" /><file name="styles.css.map" server="sftp.sd3.gpaas.net/vhosts/default/" local="3598612914" remote="3777036033" Dst="-1" /><file name="styles.css" server="sftp.sd3.gpaas.net/vhosts/thesomethinrain.work/htdocs/" local="3808367598" remote="3808369285" Dst="-1" /><file name="styles.css.map" server="sftp.sd3.gpaas.net/vhosts/thesomethinrain.work/htdocs/" local="3808367599" remote="3808369285" Dst="-1" /></dwsync>